{"id":"http://json-schema.org/draft-04/schema#","$schema":"http://json-schema.org/draft-04/schema#","title":"Grades","description":"Grades api endpoint","stability":"Prototype","strictProperties":true,"type":["object"],"definitions":{"matchID":{"description":"match id for peer review","type":"integer"},"submissionID":{"description":"submissionID for student submission","type":"integer"},"score":{"description":"score value","type":"number"},"peerReviewScore":{"type":"object","required":["matchID","score"],"additionalProperties":false,"properties":{"matchID":{"description":"match id for peer review","type":"integer"},"score":{"description":"score value","type":"number"}}},"submissionScore":{"type":"object","required":["submissionID","score"],"additionalProperties":false,"properties":{"matchID":{"description":"submissionID for student submission","type":"integer"},"score":{"description":"score value","type":"number"}}}},"links":[{"description":"Get grades for peerreviews","href":"/grades/peerreviews","title":"peerreviews","method":"GET","rel":"list","schema":{},"targetSchema":{"type":"object","requried":["scores"],"additionalProperties":false,"properties":{"scores":{"type":"array","items":{"type":"object","required":["matchID","score"],"additionalProperties":false,"properties":{"matchID":{"description":"match id for peer review","type":"integer"},"score":{"description":"score value","type":"number"}}}}}}},{"description":"Get grades from submissions","href":"/grades/submissions","title":"submissions","method":"GET","rel":"list","schema":{},"targetSchema":{"type":"object","requried":["scores"],"additionalProperties":false,"properties":{"scores":{"type":"array","items":{"type":"object","required":["submissionID","score"],"additionalProperties":false,"properties":{"matchID":{"description":"submissionID for student submission","type":"integer"},"score":{"description":"score value","type":"number"}}}}}}}]}
