{
	"title" :	"/course/create POST request",
	"$schema" :	"v1",
	"description" :	"POST /course/create request",
	"type" :	"object",
	"required" :	["courseID", "name", "displayName", "browsable", "authType", "registrationType"],
	"additionalProperties" :	false,
	"properties" :	{
			"courseID" :	{"type" : "int"},
			"name" :	{"type" : "string"},
   			"displayName" :	{"type" : "string"},
			"authType" :	{"type" : "string"},
			"registrationType" :	{"type" : "string"},
			"browsable" :	{"type" : "bool"}
		}
}
